{"countries": {"Kenya": "africa.kenya", "Madagascar": "africa.madagascar", "Nigeria": "africa.nigeria", "South Africa": "africa.safrica", "Botswana": "africa.safrica", "Eswatini": "africa.safrica", "Brazil": "americas.brazil", "Peru": "americas", "Mexico": "americas", "India": "asia.india", "Indoneisa": "asia.indonesia", "Malaysia": "asia.malaysia", "Singapore": "asia.singapore", "Australia": "australia", "Canada": "canada", "United States": "usa", "Philippines": "philippines", "Saudi Arabia": "meast.sarabia", "Yemen": "meast.sarabia", "Oman": "meast.sarabia", "United Arab Emirates": "meast.sarabia", "Israel": "meast", "Egypt": "meast", "Jordan": "meast", "Lebanon": "meast", "Syria": "meast", "Palestinian Territory": "meast", "Iraq": "meast", "Belarus": "europe.belarus", "Denmark": "europe.denmark", "Estonia": "europe.estonia", "Finland": "europe.finland", "France": "europe.france", "Ireland": "europe.ireland", "Italy": "europe.italy", "Malta": "europe.malta", "Netherlands": "europe.netherlands", "Poland": "europe.poland", "Slovakia": "europe.slovakia", "Slovenia": "europe.slovenia", "Sweden": "europe.sweden", "Isle of Man": "europe.england.liverpool.isleofman", "Jersey": "europe.england.portsmouth.jersey", "Guernsey": "europe.england.portsmouth.guernsey"}, "states": {"England": "europe.england", "Wales": "europe.wales", "Scotland": "europe.scotland", "Northern Ireland": "europe.ireland"}}
